oneredis/__init__.py
oneredis/redis_handler.py
oneredis-0.1.1.dist-info/LICENSE
oneredis-0.1.1.dist-info/METADATA
oneredis-0.1.1.dist-info/WHEEL
oneredis-0.1.1.dist-info/top_level.txt
oneredis-0.1.1.dist-info/zip-safe
oneredis-0.1.1.dist-info/RECORD
